yta_image_base/__init__.py
yta_image_base/background.py
yta_image_base/color/__init__.py
yta_image_base/color/picker.py
yta_image_base/converter.py
yta_image_base/editor/__init__.py
yta_image_base/editor/utils.py
yta_image_base/parser.py
yta_image_base/region/__init__.py
yta_image_base/region/finder.py
yta_image_base/size.py
yta_image_base-0.0.9.dist-info/LICENSE
yta_image_base-0.0.9.dist-info/METADATA
yta_image_base-0.0.9.dist-info/WHEEL
yta_image_base-0.0.9.dist-info/RECORD
