Metadata-Version: 2.3
Name: yta-image-base
Version: 0.0.9
Summary: Youtube Autonomous Image Base Module.
Author: danialcala94
Author-email: danielalcalavalera@gmail.com
Requires-Python: ==3.9
Classifier: Programming Language :: Python :: 3
Classifier: Programming Language :: Python :: 3.9
Requires-Dist: numpy (>=1.23.5,<3.0.0)
Requires-Dist: opencv-python (>=4.11.0.86,<5.0.0.0)
Requires-Dist: pillow (>=9.5.0,<19.0.0)
Requires-Dist: yta_constants (>=0.0.1,<1.0.0)
Requires-Dist: yta_file (>=0.0.1,<1.0.0)
Requires-Dist: yta_general (>=0.0.1,<1.0.0)
Requires-Dist: yta_positioning (>=0.0.1,<1.0.0)
Requires-Dist: yta_programming (>=0.0.1,<1.0.0)
Requires-Dist: yta_temp (>=0.0.1,<1.0.0)
Requires-Dist: yta_validation (>=0.0.1,<1.0.0)
Requires-Dist: yta_video_utils (>=0.0.1,<1.0.0)
